population_structure/__init__.py
population_structure/user_messages.py
population_structure/utils.py
population_structure/coalescence/__init__.py
population_structure/coalescence/coalescence.py
population_structure/data/libmigration.so
population_structure/data/libmigration_noGSL.dll
population_structure/fst/__init__.py
population_structure/fst/fst.py
population_structure/helper_funcs/__init__.py
population_structure/helper_funcs/helper_funcs.py
population_structure/matrix_generator/__init__.py
population_structure/matrix_generator/matrix_generator.py
population_structure/migration/__init__.py
population_structure/migration/migration.py
population_structure-1.0.1.dist-info/LICENSE
population_structure-1.0.1.dist-info/METADATA
population_structure-1.0.1.dist-info/WHEEL
population_structure-1.0.1.dist-info/top_level.txt
population_structure-1.0.1.dist-info/RECORD
