Metadata-Version: 2.1
Name: population_structure
Version: 1.0.1
Summary: Major changes in the the utils module. The f_to_m function previously used a numeric solver which oftenfailed due to constraining the solution with conservative migration constraints. Now, using the constraintsthe numerical solver adds the constraints as part of the equations to minimize, and it possible to runthe function without the conservative migration constraints.
Author: Eyal Haluts
Author-email: eyal.haluts@mail.huji.ac.il
Requires-Python: >=3.7
License-File: LICENSE
Requires-Dist: scipy
Requires-Dist: importlib-resources
Requires-Dist: numpy
